unitflex/__init__.py
unitflex/config.py
unitflex/data.py
unitflex/length.py
unitflex/mass.py
unitflex/pressure.py
unitflex/speed.py
unitflex/temperature.py
unitflex/time.py
unitflex/utils.py
unitflex/volume.py
unitflex-0.9.3.dist-info/licenses/LICENSE
unitflex-0.9.3.dist-info/METADATA
unitflex-0.9.3.dist-info/WHEEL
unitflex-0.9.3.dist-info/top_level.txt
unitflex-0.9.3.dist-info/RECORD
