Metadata-Version: 2.4
Name: unitflex
Version: 0.9.3
Summary: An Accurate and Flexible Unit Converter Library.
Home-page: https://github.com/zranndts/unitflex
Author: zranndts
Author-email: Zahraan Dzakii Tsaqiif <vleaxorzz@gmail.com>
License: MIT
Project-URL: Homepage, https://github.com/zranndts/unit-flex
Project-URL: Documentation, https://github.com/zranndts/unit-flex#readme
Project-URL: Source, https://github.com/zranndts/unit-flex
Project-URL: Issues, https://github.com/zranndts/unit-flex/issues
Keywords: unit conversion,conversion,python library
Classifier: Programming Language :: Python :: 3
Classifier: License :: OSI Approved :: MIT License
Classifier: Operating System :: OS Independent
Requires-Python: >=3.6
License-File: LICENSE
Dynamic: author
Dynamic: home-page
Dynamic: license-file
Dynamic: requires-python
